algo_engine/__init__.py
algo_engine/apps/__init__.py
algo_engine/apps/bokeh_server.py
algo_engine/apps/backtest/__init__.py
algo_engine/apps/backtest/doc_server.py
algo_engine/apps/backtest/tester.py
algo_engine/apps/backtest/web_app.py
algo_engine/apps/backtest/static/styles/dash.css
algo_engine/apps/backtest/templates/dash.html
algo_engine/apps/backtest/templates/index.html
algo_engine/apps/demo/__init__.py
algo_engine/apps/demo/test.py
algo_engine/apps/sim_input/__init__.py
algo_engine/apps/sim_input/client.py
algo_engine/apps/sim_input/sim_keyboard.py
algo_engine/apps/sim_input/sim_mouse.py
algo_engine/apps/sim_input/window.py
algo_engine/backtest/__init__.py
algo_engine/backtest/__main__.py
algo_engine/backtest/metrics.py
algo_engine/backtest/replay.py
algo_engine/backtest/sim_match.py
algo_engine/base/__init__.py
algo_engine/base/c_heap_allocator.c
algo_engine/base/c_heap_allocator.cpython-313-x86_64-linux-gnu.so
algo_engine/base/c_heap_allocator.h
algo_engine/base/c_heap_allocator.pxd
algo_engine/base/c_heap_allocator.pyi
algo_engine/base/c_heap_allocator.pyx
algo_engine/base/c_intern_string.c
algo_engine/base/c_intern_string.cpython-313-x86_64-linux-gnu.so
algo_engine/base/c_intern_string.h
algo_engine/base/c_intern_string.pxd
algo_engine/base/c_intern_string.pyi
algo_engine/base/c_intern_string.pyx
algo_engine/base/c_shm_allocator.c
algo_engine/base/c_shm_allocator.cpython-313-x86_64-linux-gnu.so
algo_engine/base/c_shm_allocator.h
algo_engine/base/c_shm_allocator.pxd
algo_engine/base/c_shm_allocator.pyi
algo_engine/base/c_shm_allocator.pyx
algo_engine/base/console_utils.py
algo_engine/base/finance_decimal.py
algo_engine/base/technical_analysis.py
algo_engine/base/telemetrics.py
algo_engine/base/c_market_data/__init__.pxd
algo_engine/base/c_market_data/__init__.py
algo_engine/base/c_market_data/c_candlestick.c
algo_engine/base/c_market_data/c_candlestick.cpython-313-x86_64-linux-gnu.so
pyalgoengine-0.9.4.post1.dist-info/METADATA
pyalgoengine-0.9.4.post1.dist-info/WHEEL
pyalgoengine-0.9.4.post1.dist-info/top_level.txt
pyalgoengine-0.9.4.post1.dist-info/RECORD
pyalgoengine-0.9.4.post1.dist-info/licenses/LICENSE
